{
  "type": "ThermalGenerator",
  "name": "Turbine Concentrator",
  "description": "Similar to a Turbine Condenser but creates larger amounts of power and more water.",
  "health": 1550,
  "size": 3,
  "attribute": "steam",
  "displayEfficiencyScale": 1,
  "minEfficiency": 8.999,
  "powerProduction": 0.85,
  "displayEfficiency": false,
  "generateEffect": "turbinegenerate",
  "effectChance": 0.05,
  "category": "power",
  "research": "turbine-condenser",
  "requirements": [
    "beryllium/90",
    "graphite/75",
    "tungsten/50"
  ],
  "ambientSound": "hum",
  "ambientSoundVolume": 0.10,
  "drawer": {
    "type": "DrawMulti",
    "drawers": [
      {
        "type": "DrawDefault" 
      },
      {
        "type": "DrawBlurSpin",
        "suffix": "-rotator",
        "rotateSpeed": 10.8,
        "blurThresh": 0.01
      }
    ]
  },
  "hasLiquids": true,
  "outputLiquid": "water/0.25",
  "fogRadius": 3,
  "researchCost": [
    "beryllium/180",
    "graphite/150",
    "tungsten/120"
  ]
}
